jenkins/__init__.py
jenkins/plugins.py
jenkins/version.py
python_jenkins_checkmk_retry_parameter-1.8.3.dev8.dist-info/AUTHORS
python_jenkins_checkmk_retry_parameter-1.8.3.dev8.dist-info/COPYING
python_jenkins_checkmk_retry_parameter-1.8.3.dev8.dist-info/METADATA
python_jenkins_checkmk_retry_parameter-1.8.3.dev8.dist-info/WHEEL
python_jenkins_checkmk_retry_parameter-1.8.3.dev8.dist-info/RECORD
