Metadata-Version: 2.1
Name: python-jenkins-checkmk-retry-parameter
Version: 1.8.3.dev8
Summary: Python bindings for the remote Jenkins API, custom package until official release
Author: Ken Conley
Author-email: kwc@willowgarage.com
Requires-Python: >=3.10.4,<4.0.0
Classifier: Programming Language :: Python :: 3
Classifier: Programming Language :: Python :: 3.11
Classifier: Programming Language :: Python :: 3.12
Classifier: Programming Language :: Python :: 3.13
Requires-Dist: multi_key_dict
Requires-Dist: pbr (>=6.1.1,<7.0.0)
Requires-Dist: requests
Project-URL: Documentation, https://python-jenkins.readthedocs.io/
Project-URL: Repository, https://opendev.org/jjb/python-jenkins
